{"trades":[{"row_number":56,"trade_id":"T55","date":"2025-12-17","symbol":"ESH6","side":"Long","contracts":3,"entry_time":"10:38:15","entry_price":6872,"stop_price":"","target_price":"","exit_time":"10:41:14","exit_price":6872,"fees":14.04,"p_l net":"","p_l":0,"setup":"","session":"","score":"","notes":"","screenshot":"","pre_trade":"","trade_entry":"","trade_management":"","trade_exit":"","screenshot_url_A":""},{"row_number":55,"trade_id":"T54","date":"2025-12-17","symbol":"NQH6","side":"Long","contracts":1,"entry_time":"10:15:46","entry_price":25434.5,"stop_price":"","target_price":"","exit_time":"10:21:19","exit_price":25434,"fees":4.68,"p_l net":"","p_l":-10,"setup":"","session":"","score":"","notes":"","screenshot":"","pre_trade":"","trade_entry":"","trade_management":"","trade_exit":"","screenshot_url_A":""},{"row_number":54,"trade_id":"T53","date":"2025-12-17","symbol":"GCG6","side":"Short","contracts":1,"entry_time":"10:13:39","entry_price":4349,"stop_price":"","target_price":"","exit_time":"10:15:00","exit_price":4350.1,"fees":5.02,"p_l net":"","p_l":-110,"setup":"","session":"","score":"","notes":"","screenshot":"","pre_trade":"","trade_entry":"","trade_management":"","trade_exit":"","screenshot_url_A":""},{"row_number":53,"trade_id":"T52","date":"2025-12-17","symbol":"NQH6","side":"Long","contracts":1,"entry_time":"9:59:31","entry_price":25416.5,"stop_price":"","target_price":"","exit_time":"10:00:19","exit_price":25408.5,"fees":4.68,"p_l net":"","p_l":-160,"setup":"","session":"","score":"","notes":"","screenshot":"","pre_trade":"","trade_entry":"","trade_management":"","trade_exit":"","screenshot_url_A":""},{"row_number":52,"trade_id":"T51","date":"2025-12-17","symbol":"GCG6","side":"Long","contracts":1,"entry_time":"9:49:58","entry_price":4347.9,"stop_price":"","target_price":"","exit_time":"9:52:05","exit_price":4348.6,"fees":5.02,"p_l net":"","p_l":70,"setup":"","session":"","score":"","notes":"","screenshot":"","pre_trade":"","trade_entry":"","trade_management":"","trade_exit":"","screenshot_url_A":""},{"row_number":51,"trade_id":"T50","date":"2025-12-17","symbol":"NQH6","side":"Long","contracts":1,"entry_time":"9:45:12","entry_price":25426.5,"stop_price":"","target_price":"","exit_time":"9:49:21","exit_price":25426.75,"fees":4.68,"p_l net":"","p_l":5,"setup":"","session":"","score":"","notes":"","screenshot":"","pre_trade":"","trade_entry":"","trade_management":"","trade_exit":"","screenshot_url_A":""},{"row_number":50,"trade_id":"T49","date":"2025-12-17","symbol":"GCG6","side":"Long","contracts":1,"entry_time":"9:40:49","entry_price":4348.8,"stop_price":"","target_price":"","exit_time":"9:43:27","exit_price":4346.4,"fees":5.02,"p_l net":"","p_l":-240,"setup":"","session":"","score":"","notes":"","screenshot":"","pre_trade":"","trade_entry":"","trade_management":"","trade_exit":"","screenshot_url_A":""},{"row_number":49,"trade_id":"T48","date":"2025-12-17","symbol":"NQH6","side":"Long","contracts":1,"entry_time":"9:38:24","entry_price":25425.5,"stop_price":"","target_price":"","exit_time":"9:41:08","exit_price":25418.5,"fees":4.68,"p_l net":"","p_l":-140,"setup":"","session":"","score":"","notes":"","screenshot":"","pre_trade":"","trade_entry":"","trade_management":"","trade_exit":"","screenshot_url_A":""},{"row_number":48,"trade_id":"T47","date":"2025-12-17","symbol":"MGCG6","side":"Long","contracts":6,"entry_time":"9:23:54","entry_price":4346.3,"stop_price":"","target_price":"","exit_time":"9:25:21","exit_price":4343.8,"fees":12.24,"p_l net":"","p_l":-150,"setup":"","session":"","score":"","notes":"","screenshot":"","pre_trade":"","trade_entry":"","trade_management":"","trade_exit":"","screenshot_url_A":""},{"row_number":47,"trade_id":"T46","date":"2025-12-16","symbol":"NQH6","side":"Long","contracts":1,"entry_time":"11:13:03","entry_price":25204,"stop_price":"","target_price":"","exit_time":"11:18:33","exit_price":25228.75,"fees":4.68,"p_l net":"","p_l":495,"setup":"","session":"","score":"","notes":"","screenshot":"https://drive.google.com/file/d/1m9J9yPHejV3Kz-02vbFlXNzyYzDt9igS/view?usp=drivesdk","pre_trade":"","trade_entry":"","trade_management":"","trade_exit":"","screenshot_url_A":"https://drive.google.com/file/d/1m9J9yPHejV3Kz-02vbFlXNzyYzDt9igS/view?usp=drivesdk"},{"row_number":46,"trade_id":"T45","date":"2025-12-16","symbol":"GCG6","side":"Short","contracts":1,"entry_time":"11:10:25","entry_price":4304.2,"stop_price":"","target_price":"","exit_time":"11:12:30","exit_price":4306.5,"fees":5.02,"p_l net":"","p_l":-230,"setup":"","session":"","score":"","notes":"","screenshot":"https://drive.google.com/file/d/15ErQYu40KT4tRbHRmM5Sec81ugKWSrYN/view?usp=drivesdk","pre_trade":"","trade_entry":"","trade_management":"","trade_exit":"","screenshot_url_A":"https://drive.google.com/file/d/15ErQYu40KT4tRbHRmM5Sec81ugKWSrYN/view?usp=drivesdk"},{"row_number":45,"trade_id":"T44","date":"2025-12-16","symbol":"NQH6","side":"Long","contracts":1,"entry_time":"11:05:32","entry_price":25196,"stop_price":"","target_price":"","exit_time":"11:08:35","exit_price":25195.5,"fees":4.68,"p_l net":"","p_l":-10,"setup":"","session":"","score":"","notes":"","screenshot":"https://drive.google.com/file/d/1MzD2ye-HYMnWYlCoxfQrEoAyoKYj6Nf5/view?usp=drivesdk","pre_trade":"","trade_entry":"","trade_management":"","trade_exit":"","screenshot_url_A":"https://drive.google.com/file/d/1MzD2ye-HYMnWYlCoxfQrEoAyoKYj6Nf5/view?usp=drivesdk"},{"row_number":44,"trade_id":"T43","date":"2025-12-16","symbol":"GCG6","side":"Long","contracts":1,"entry_time":"11:01:03","entry_price":4308.5,"stop_price":"","target_price":"","exit_time":"11:02:09","exit_price":4307.8,"fees":5.02,"p_l net":"","p_l":-70,"setup":"","session":"","score":"","notes":"","screenshot":"https://drive.google.com/file/d/1FpC8oA6kH41p6Dvv36Blw7pB8rKQvR3u/view?usp=drivesdk","pre_trade":"","trade_entry":"","trade_management":"","trade_exit":"","screenshot_url_A":"https://drive.google.com/file/d/1FpC8oA6kH41p6Dvv36Blw7pB8rKQvR3u/view?usp=drivesdk"},{"row_number":43,"trade_id":"T42","date":"2025-12-16","symbol":"NQH6","side":"Short","contracts":1,"entry_time":"10:51:09","entry_price":25179,"stop_price":"","target_price":"","exit_time":"10:57:59","exit_price":25179.25,"fees":4.68,"p_l net":"","p_l":-5,"setup":"","session":"","score":"","notes":"","screenshot":"https://drive.google.com/file/d/1MfAwgi7ARTF7o1sw32iBzeOa4ao1i-2y/view?usp=drivesdk","pre_trade":"","trade_entry":"","trade_management":"","trade_exit":"","screenshot_url_A":"https://drive.google.com/file/d/1MfAwgi7ARTF7o1sw32iBzeOa4ao1i-2y/view?usp=drivesdk"},{"row_number":42,"trade_id":"T41","date":"2025-12-16","symbol":"GCG6","side":"Short","contracts":1,"entry_time":"10:50:43","entry_price":4305.3,"stop_price":"","target_price":"","exit_time":"10:54:44","exit_price":4305.1,"fees":5.02,"p_l net":"","p_l":20,"setup":"","session":"","score":"","notes":"","screenshot":"https://drive.google.com/file/d/1-OYsJ-PlekNTgKODg9HOerH_VRIb6Y3R/view?usp=drivesdk","pre_trade":"","trade_entry":"","trade_management":"","trade_exit":"","screenshot_url_A":"https://drive.google.com/file/d/1-OYsJ-PlekNTgKODg9HOerH_VRIb6Y3R/view?usp=drivesdk"},{"row_number":41,"trade_id":"T40","date":"2025-12-16","symbol":"NQH6","side":"Long","contracts":1,"entry_time":"9:45:03","entry_price":25193.5,"stop_price":"","target_price":"","exit_time":"9:47:31","exit_price":25198,"fees":4.68,"p_l net":"","p_l":90,"setup":"","session":"","score":"","notes":"","screenshot":"","pre_trade":"","trade_entry":"","trade_management":"","trade_exit":"","screenshot_url_A":""},{"row_number":40,"trade_id":"T39","date":"2025-12-16","symbol":"GCG6","side":"Long","contracts":1,"entry_time":"9:44:01","entry_price":4309.1,"stop_price":"","target_price":"","exit_time":"9:52:33","exit_price":4311.3,"fees":5.02,"p_l net":"","p_l":220,"setup":"","session":"","score":"","notes":"","screenshot":"","pre_trade":"","trade_entry":"","trade_management":"","trade_exit":"","screenshot_url_A":""},{"row_number":39,"trade_id":"T38","date":"2025-12-16","symbol":"NQH6","side":"Short","contracts":1,"entry_time":"9:35:18","entry_price":25172,"stop_price":"","target_price":"","exit_time":"9:43:37","exit_price":25187.25,"fees":4.68,"p_l net":"","p_l":-305,"setup":"","session":"","score":"","notes":"","screenshot":"","pre_trade":"","trade_entry":"","trade_management":"","trade_exit":"","screenshot_url_A":""},{"row_number":38,"trade_id":"T37","date":"2025-12-15","symbol":"GCG6","side":"Short","contracts":1,"entry_time":"11:30:36","entry_price":4376.1,"stop_price":"","target_price":"","exit_time":"11:31:53","exit_price":4373.3,"fees":5.02,"p_l net":"","p_l":280,"setup":"","session":"","score":4,"notes":"Lucky to spot this trade as I was completing the notes for the previous trades. Noticed significantly large bearish candle. At first, had the mentality of not wanting to enter as I had just had a win and didn't want to lose profits. Managed to overcome and enter anyway. Entry was good as I was patient, waited for entry candle to retrace first, then saw volatility to the downside so made my entry then. This helped improve RR as I was then able to place SL above upper VWAP band - as price was more likely to continue its bearish momentum. Emotional state - wasn't confident and flowing. Felt fear of losing money, also had to remind myself to let the trade play out. Even though I wanted to close the trade early and take profit, I had to keep reminding myself that I am already in profit, and that whatever comes from this is a bonus.","screenshot":"https://drive.google.com/file/d/1kLPaO32CHtkM_Gh5PS0xRZjYp1VR7RQp/view?usp=drivesdk","pre_trade":"Complete Prep","trade_entry":"Followed Plan","trade_management":"Followed Plan","trade_exit":"Followed Plan","screenshot_url_A":"https://drive.google.com/file/d/1kLPaO32CHtkM_Gh5PS0xRZjYp1VR7RQp/view?usp=drivesdk"},{"row_number":37,"trade_id":"T36","date":"2025-12-15","symbol":"GCG6","side":"Long","contracts":2,"entry_time":"11:19:13","entry_price":4379,"stop_price":"","target_price":"","exit_time":"11:26:32","exit_price":4382,"fees":10.04,"p_l net":"","p_l":600,"setup":"","session":"","score":4,"notes":"In review, the entry candle is as close to an A+ set up as we can be. First positioning box represents ideal entry, the other represents actual entry. Happy that I was able to react quickly after loss and then execute again. Emotions were fine. I think I felt focused and locked in. In hindsight, potentially risked too much, however I was very tight with SL - closer than typical entry for this strategy. This does pose the question about my max DD for the day.","screenshot":"https://drive.google.com/file/d/1Thu0ZLFYMlwY1K5TRRvif4-mbRcNtOUR/view?usp=drivesdk","pre_trade":"Complete Prep","trade_entry":"Followed Plan","trade_management":"Followed Plan","trade_exit":"Followed Plan","screenshot_url_A":"https://drive.google.com/file/d/1Thu0ZLFYMlwY1K5TRRvif4-mbRcNtOUR/view?usp=drivesdk"},{"row_number":36,"trade_id":"T35","date":"2025-12-15","symbol":"GCG6","side":"Short","contracts":1,"entry_time":"11:16:52","entry_price":4376.4,"stop_price":"","target_price":"","exit_time":"11:17:22","exit_price":4377.9,"fees":5.02,"p_l net":"","p_l":-150,"setup":"","session":"","score":2,"notes":"Unfortunate mistake here. Tried to force this trade. No real set-up. Needed a strong candle like trade before to validate any type of entry here. Need to work on minimizing these mistakes as much as possible. Emotions were a mix of FOMO, really wanting the short to happen and then frustration for making the mistake and then losing money.","screenshot":"https://drive.google.com/file/d/1xD50aNj4EhsYG8h6mjPC_nvQ2iIoxMUO/view?usp=drivesdk","pre_trade":"Complete Prep","trade_entry":"Major Deviation","trade_management":"Followed Plan","trade_exit":"Followed Plan","screenshot_url_A":"https://drive.google.com/file/d/1xD50aNj4EhsYG8h6mjPC_nvQ2iIoxMUO/view?usp=drivesdk"},{"row_number":35,"trade_id":"T34","date":"2025-12-15","symbol":"GCG6","side":"Short","contracts":1,"entry_time":"10:53:02","entry_price":4376.3,"stop_price":"","target_price":"","exit_time":"11:02:46","exit_price":4377.1,"fees":5.02,"p_l net":"","p_l":-80,"setup":"","session":"","score":2,"notes":"Entry signal not 100% to plan, however candle shape and size gave me enough confidence to enter. Price pulled back strongly after entry, happy with myself as I let trade be and didn't close early or panic. Slight issue with trade management. Once trade was in profit, I didn't move SL to BE. Sometimes this works, however with shorts, especially fading a bullish trend, it's always better to protect account. Emotions were calm and focused for most of the trade. Then a little bit of confusion and stress about where to place my SL.","screenshot":"https://drive.google.com/file/d/1HdbXwkVfvt1d2Z0sdL_jpXJ-1-iY6OWh/view?usp=drivesdk","pre_trade":"Complete Prep","trade_entry":"Minor Deviation","trade_management":"Minor Deviation","trade_exit":"Followed Plan","screenshot_url_A":"https://drive.google.com/file/d/1HdbXwkVfvt1d2Z0sdL_jpXJ-1-iY6OWh/view?usp=drivesdk"},{"row_number":34,"trade_id":"T33","date":"2025-12-12","symbol":"GCG6","side":"Long","contracts":1,"entry_time":"14:04:00","entry_price":4366.4,"stop_price":"","target_price":"","exit_time":"14:11:00","exit_price":4372.3,"fees":5.02,"p_l net":"","p_l":590,"setup":"","session":"","score":2,"notes":"No clear entry signal and at the time of the trade, I don't think I recognized what I do now. Happy that I entered, however it was more for the wrong reasons, rather than the underlying confluences. Still a revenge trade, however the question remains, if this trade didn't play out, would I be able to handle the loss mentally? Would I switch to TILT mode? Most likely yes. Which is why it is important that I keep my emotions in check. Also this renewed sense of purpose. Strengthen the connection as to why I am doing this, why it is important to not resort to TILT and blowing accounts for the sake of being 'right'. I have to remember this is for Dad. The same old patterns will never allow me to achieve what I want. I need to think and behave differently.","screenshot":"https://drive.google.com/file/d/1GJns3VhWQDcPav35CHq27BPlyDMGZ2AI/view?usp=drivesdk","pre_trade":"No Prep","trade_entry":"Followed Plan","trade_management":"Followed Plan","trade_exit":"Followed Plan","screenshot_url_A":"https://drive.google.com/file/d/1GJns3VhWQDcPav35CHq27BPlyDMGZ2AI/view?usp=drivesdk"},{"row_number":33,"trade_id":"T32","date":"2025-12-12","symbol":"NQZ5","side":"Short","contracts":1,"entry_time":"10:07:21","entry_price":25655,"stop_price":"","target_price":"","exit_time":"10:08:51","exit_price":25640.75,"fees":4.68,"p_l net":"","p_l":285,"setup":"","session":"","score":4,"notes":"Feel a bit fucked off. Missed the first trade and from there just kept getting stopped out. Very frustrating. Price is currently very choppy, best decision would be to walk away. Fucking Friday's always seem to fuck me over. Went long once again, even though I kept telling myself to wait for a clearer or new opportunity. This is the type of situation that fucks me over on a live account.","screenshot":"https://drive.google.com/file/d/1hbMuJoYpbm0VOmnmuynyHQ_tcqZ9zTdc/view?usp=drivesdk","pre_trade":"Complete Prep","trade_entry":"Followed Plan","trade_management":"Followed Plan","trade_exit":"Followed Plan","screenshot_url_A":"https://drive.google.com/file/d/1hbMuJoYpbm0VOmnmuynyHQ_tcqZ9zTdc/view?usp=drivesdk"},{"row_number":32,"trade_id":"T31","date":"2025-12-12","symbol":"NQZ5","side":"Long","contracts":1,"entry_time":"09:50:44","entry_price":25667.5,"stop_price":"","target_price":"","exit_time":"9:52:51","exit_price":25671,"fees":4.68,"p_l net":"","p_l":70,"setup":"","session":"","score":"","notes":"","screenshot":"","pre_trade":"","trade_entry":"","trade_management":"","trade_exit":"","screenshot_url_A":""},{"row_number":31,"trade_id":"T30","date":"2025-12-12","symbol":"ESZ5","side":"Short","contracts":2,"entry_time":"09:45:49","entry_price":6909.25,"stop_price":"","target_price":"","exit_time":"9:47:43","exit_price":6908.75,"fees":9.36,"p_l net":"","p_l":50,"setup":"","session":"","score":"","notes":"","screenshot":"","pre_trade":"","trade_entry":"","trade_management":"","trade_exit":"","screenshot_url_A":""},{"row_number":30,"trade_id":"T29","date":"2025-12-12","symbol":"NQZ5","side":"Long","contracts":1,"entry_time":"09:39:11","entry_price":25680.75,"stop_price":"","target_price":"","exit_time":"9:43:59","exit_price":25672.75,"fees":4.68,"p_l net":"","p_l":-160,"setup":"","session":"","score":"","notes":"","screenshot":"","pre_trade":"","trade_entry":"","trade_management":"","trade_exit":"","screenshot_url_A":""},{"row_number":29,"trade_id":"T28","date":"2025-12-12","symbol":"NQZ5","side":"Long","contracts":1,"entry_time":"09:20:13","entry_price":25679,"stop_price":"","target_price":"","exit_time":"9:25:12","exit_price":25670.5,"fees":4.68,"p_l net":"","p_l":-170,"setup":"","session":"","score":"","notes":"","screenshot":"","pre_trade":"","trade_entry":"","trade_management":"","trade_exit":"","screenshot_url_A":""},{"row_number":28,"trade_id":"T27","date":"2025-12-12","symbol":"NQZ5","side":"Long","contracts":1,"entry_time":"09:09:33","entry_price":25678.5,"stop_price":"","target_price":"","exit_time":"9:15:21","exit_price":25673.25,"fees":4.68,"p_l net":"","p_l":-105,"setup":"","session":"","score":"","notes":"","screenshot":"","pre_trade":"","trade_entry":"","trade_management":"","trade_exit":"","screenshot_url_A":""},{"row_number":27,"trade_id":"T26","date":"2025-12-12","symbol":"NQZ5","side":"Long","contracts":1,"entry_time":"09:05:25","entry_price":25673.5,"stop_price":"","target_price":"","exit_time":"9:08:12","exit_price":25670.25,"fees":4.68,"p_l net":"","p_l":-65,"setup":"","session":"","score":"","notes":"","screenshot":"","pre_trade":"","trade_entry":"","trade_management":"","trade_exit":"","screenshot_url_A":""},{"row_number":26,"trade_id":"T25","date":"2025-12-11","symbol":"GCG6","side":"Short","contracts":1,"entry_time":"11:16:56","entry_price":4248.1,"stop_price":"","target_price":"","exit_time":"11:21:46","exit_price":4246.5,"fees":5.02,"p_l net":"","p_l":160,"setup":"","session":"","score":"","notes":"","screenshot":"","pre_trade":"","trade_entry":"","trade_management":"","trade_exit":"","screenshot_url_A":""},{"row_number":25,"trade_id":"T24","date":"2025-12-11","symbol":"GCG6","side":"Short","contracts":1,"entry_time":"11:10:13","entry_price":4250.7,"stop_price":"","target_price":"","exit_time":"11:12:13","exit_price":4250.9,"fees":5.02,"p_l net":"","p_l":-20,"setup":"","session":"","score":"","notes":"","screenshot":"","pre_trade":"","trade_entry":"","trade_management":"","trade_exit":"","screenshot_url_A":""},{"row_number":24,"trade_id":"T23","date":"2025-12-11","symbol":"GCG6","side":"Short","contracts":1,"entry_time":"10:09:28","entry_price":4238.3,"stop_price":"","target_price":"","exit_time":"10:13:44","exit_price":4240.2,"fees":5.02,"p_l net":"","p_l":-190,"setup":"","session":"","score":"","notes":"","screenshot":"","pre_trade":"","trade_entry":"","trade_management":"","trade_exit":"","screenshot_url_A":""},{"row_number":23,"trade_id":"T22","date":"2025-12-11","symbol":"NQZ5","side":"Long","contracts":1,"entry_time":"10:07:02","entry_price":25561,"stop_price":"","target_price":"","exit_time":"10:25:23","exit_price":25586.5,"fees":4.68,"p_l net":"","p_l":510,"setup":"","session":"","score":"","notes":"","screenshot":"https://drive.google.com/file/d/1QvXqopIqPiJ05umVJAfNqDvM6aBj6KGb/view?usp=drivesdk","pre_trade":"","trade_entry":"","trade_management":"","trade_exit":"","screenshot_url_A":"https://drive.google.com/file/d/1QvXqopIqPiJ05umVJAfNqDvM6aBj6KGb/view?usp=drivesdk"},{"row_number":22,"trade_id":"T21","date":"2025-12-10","symbol":"NQZ5","side":"Short","contracts":1,"entry_time":"16:52:38","entry_price":25595,"stop_price":"","target_price":"","exit_time":"16:55:14","exit_price":25564,"fees":4.68,"p_l net":"","p_l":620,"setup":"","session":"","score":"","notes":"","screenshot":"","pre_trade":"","trade_entry":"","trade_management":"","trade_exit":"","screenshot_url_A":""},{"row_number":21,"trade_id":"T20","date":"2025-12-10","symbol":"NQZ5","side":"Long","contracts":1,"entry_time":"16:49:29","entry_price":25613.75,"stop_price":"","target_price":"","exit_time":"16:51:36","exit_price":25611.25,"fees":4.68,"p_l net":"","p_l":-50,"setup":"","session":"","score":"","notes":"","screenshot":"","pre_trade":"","trade_entry":"","trade_management":"","trade_exit":"","screenshot_url_A":""},{"row_number":20,"trade_id":"T19","date":"2025-12-10","symbol":"ESZ5","side":"Long","contracts":1,"entry_time":"16:43:58","entry_price":6842.5,"stop_price":"","target_price":"","exit_time":"16:44:48","exit_price":6841.75,"fees":4.68,"p_l net":"","p_l":-37.5,"setup":"","session":"","score":"","notes":"","screenshot":"","pre_trade":"","trade_entry":"","trade_management":"","trade_exit":"","screenshot_url_A":""},{"row_number":19,"trade_id":"T18","date":"2025-12-10","symbol":"NQZ5","side":"Short","contracts":1,"entry_time":"16:36:30","entry_price":25591,"stop_price":"","target_price":"","exit_time":"16:37:52","exit_price":25584,"fees":4.68,"p_l net":"","p_l":140,"setup":"","session":"","score":"","notes":"","screenshot":"","pre_trade":"","trade_entry":"","trade_management":"","trade_exit":"","screenshot_url_A":""},{"row_number":18,"trade_id":"T17","date":"2025-12-10","symbol":"GCG6","side":"Long","contracts":1,"entry_time":"16:29:08","entry_price":4223.8,"stop_price":"","target_price":"","exit_time":"16:38:22","exit_price":4224.5,"fees":5.02,"p_l net":"","p_l":70,"setup":"","session":"","score":"","notes":"","screenshot":"","pre_trade":"","trade_entry":"","trade_management":"","trade_exit":"","screenshot_url_A":""},{"row_number":17,"trade_id":"T16","date":"2025-12-10","symbol":"GCG6","side":"Long","contracts":1,"entry_time":"16:02:14","entry_price":4227,"stop_price":"","target_price":"","exit_time":"16:07:03","exit_price":4227.4,"fees":5.02,"p_l net":"","p_l":40,"setup":"","session":"","score":"","notes":"","screenshot":"","pre_trade":"","trade_entry":"","trade_management":"","trade_exit":"","screenshot_url_A":""},{"row_number":16,"trade_id":"T15","date":"2025-12-10","symbol":"NQZ5","side":"Short","contracts":1,"entry_time":"15:52:06","entry_price":25630.75,"stop_price":"","target_price":"","exit_time":"15:57:01","exit_price":25611,"fees":4.68,"p_l net":"","p_l":395,"setup":"","session":"","score":"","notes":"","screenshot":"","pre_trade":"","trade_entry":"","trade_management":"","trade_exit":"","screenshot_url_A":""},{"row_number":15,"trade_id":"T14","date":"2025-12-10","symbol":"NQZ5","side":"Long","contracts":2,"entry_time":"14:21:20","entry_price":25689.75,"stop_price":"","target_price":"","exit_time":"14:23:05","exit_price":25694.5,"fees":9.36,"p_l net":"","p_l":190,"setup":"","session":"","score":"","notes":"","screenshot":"","pre_trade":"","trade_entry":"","trade_management":"","trade_exit":"","screenshot_url_A":""},{"row_number":14,"trade_id":"T13","date":"2025-12-10","symbol":"GCG6","side":"Short","contracts":1,"entry_time":"14:20:38","entry_price":4222,"stop_price":"","target_price":"","exit_time":"14:21:57","exit_price":4224.3,"fees":5.02,"p_l net":"","p_l":-230,"setup":"","session":"","score":"","notes":"","screenshot":"","pre_trade":"","trade_entry":"","trade_management":"","trade_exit":"","screenshot_url_A":""},{"row_number":13,"trade_id":"T12","date":"2025-12-10","symbol":"NQZ5","side":"Long","contracts":1,"entry_time":"14:18:59","entry_price":25669.5,"stop_price":"","target_price":"","exit_time":"14:20:25","exit_price":25678,"fees":4.68,"p_l net":"","p_l":170,"setup":"","session":"","score":"","notes":"","screenshot":"","pre_trade":"","trade_entry":"","trade_management":"","trade_exit":"","screenshot_url_A":""},{"row_number":12,"trade_id":"T11","date":"2025-12-10","symbol":"GCG6","side":"Short","contracts":1,"entry_time":"14:13:21","entry_price":4222.5,"stop_price":"","target_price":"","exit_time":"14:16:17","exit_price":4225.5,"fees":5.02,"p_l net":"","p_l":-300,"setup":"","session":"","score":"","notes":"","screenshot":"","pre_trade":"","trade_entry":"","trade_management":"","trade_exit":"","screenshot_url_A":""},{"row_number":11,"trade_id":"T10","date":"2025-12-10","symbol":"NQZ5","side":"Long","contracts":1,"entry_time":"14:11:00","entry_price":25657,"stop_price":"","target_price":"","exit_time":"14:20:25","exit_price":25678,"fees":4.68,"p_l net":"","p_l":420,"setup":"","session":"","score":"","notes":"","screenshot":"","pre_trade":"","trade_entry":"","trade_management":"","trade_exit":"","screenshot_url_A":""},{"row_number":10,"trade_id":"T9","date":"2025-12-10","symbol":"GCG6","side":"Long","contracts":1,"entry_time":"14:07:30","entry_price":4227.7,"stop_price":"","target_price":"","exit_time":"14:11:36","exit_price":4224.2,"fees":5.02,"p_l net":"","p_l":-350,"setup":"","session":"","score":"","notes":"","screenshot":"","pre_trade":"","trade_entry":"","trade_management":"","trade_exit":"","screenshot_url_A":""},{"row_number":9,"trade_id":"T8","date":"2025-12-10","symbol":"NQZ5","side":"Short","contracts":1,"entry_time":"11:13:21","entry_price":25698,"stop_price":"","target_price":"","exit_time":"11:14:25","exit_price":25704.75,"fees":4.68,"p_l net":"","p_l":-135,"setup":"","session":"","score":"","notes":"","screenshot":"","pre_trade":"","trade_entry":"","trade_management":"","trade_exit":"","screenshot_url_A":""},{"row_number":8,"trade_id":"T7","date":"2025-12-10","symbol":"NQZ5","side":"Short","contracts":1,"entry_time":"11:07:31","entry_price":25704.25,"stop_price":"","target_price":"","exit_time":"11:14:24","exit_price":25704,"fees":4.68,"p_l net":"","p_l":5,"setup":"","session":"","score":"","notes":"","screenshot":"","pre_trade":"","trade_entry":"","trade_management":"","trade_exit":"","screenshot_url_A":""},{"row_number":7,"trade_id":"T6","date":"2025-12-10","symbol":"NQZ5","side":"Short","contracts":1,"entry_time":"11:00:29","entry_price":25709.5,"stop_price":"","target_price":"","exit_time":"11:01:07","exit_price":25716,"fees":4.68,"p_l net":"","p_l":-130,"setup":"","session":"","score":"","notes":"","screenshot":"","pre_trade":"","trade_entry":"","trade_management":"","trade_exit":"","screenshot_url_A":""},{"row_number":6,"trade_id":"T5","date":"2025-12-10","symbol":"NQZ5","side":"Long","contracts":1,"entry_time":"10:49:03","entry_price":25718.5,"stop_price":"","target_price":"","exit_time":"10:56:00","exit_price":25711,"fees":4.68,"p_l net":"","p_l":-150,"setup":"","session":"","score":"","notes":"","screenshot":"","pre_trade":"","trade_entry":"","trade_management":"","trade_exit":"","screenshot_url_A":""},{"row_number":5,"trade_id":"T4","date":"2025-12-10","symbol":"NQZ5","side":"Short","contracts":1,"entry_time":"10:35:19","entry_price":25709,"stop_price":"","target_price":"","exit_time":"10:48:39","exit_price":25714,"fees":4.68,"p_l net":"","p_l":-100,"setup":"","session":"","score":"","notes":"","screenshot":"","pre_trade":"","trade_entry":"","trade_management":"","trade_exit":"","screenshot_url_A":""},{"row_number":4,"trade_id":"T3","date":"2025-12-10","symbol":"NQZ5","side":"Short","contracts":1,"entry_time":"10:23:36","entry_price":25712.5,"stop_price":"","target_price":"","exit_time":"10:29:59","exit_price":25714.25,"fees":4.68,"p_l net":"","p_l":-35,"setup":"","session":"","score":"","notes":"","screenshot":"","pre_trade":"","trade_entry":"","trade_management":"","trade_exit":"","screenshot_url_A":""},{"row_number":3,"trade_id":"T2","date":"2025-12-10","symbol":"NQZ5","side":"Short","contracts":1,"entry_time":"10:16:54","entry_price":25709,"stop_price":"","target_price":"","exit_time":"10:29:59","exit_price":25714.25,"fees":4.68,"p_l net":"","p_l":-105,"setup":"","session":"","score":2,"notes":"","screenshot":"","pre_trade":"Complete Prep","trade_entry":"Followed Plan","trade_management":"Minor Deviation","trade_exit":"Minor Deviation","screenshot_url_A":""},{"row_number":2,"trade_id":"T1","date":"2025-12-10","symbol":"NQZ5","side":"Short","contracts":1,"entry_time":"10:16:26","entry_price":25703.75,"stop_price":"","target_price":"","exit_time":"10:22:20","exit_price":25717.25,"fees":4.68,"p_l net":"","p_l":-270,"setup":"","session":"","score":4,"notes":"","screenshot":"","pre_trade":"Complete Prep","trade_entry":"Followed Plan","trade_management":"Followed Plan","trade_exit":"Followed Plan","screenshot_url_A":""}],"symbols":{"NQZ5":{"pnl":1330,"trades":22,"wins":10},"GCG6":{"pnl":80,"trades":20,"wins":9},"ESZ5":{"pnl":12.5,"trades":2,"wins":1},"NQH6":{"pnl":-40,"trades":9,"wins":3},"MGCG6":{"pnl":-150,"trades":1,"wins":0},"ESH6":{"pnl":0,"trades":1,"wins":0}},"weekdays":{"Wednesday":{"pnl":-577.5,"trades":30},"Thursday":{"pnl":460,"trades":4},"Friday":{"pnl":495,"trades":8},"Monday":{"pnl":650,"trades":4},"Tuesday":{"pnl":205,"trades":9}},"hours":{"9":{"pnl":-990,"trades":15},"10":{"pnl":-240,"trades":14},"11":{"pnl":795,"trades":12},"14":{"pnl":490,"trades":7},"15":{"pnl":395,"trades":1},"16":{"pnl":782.5,"trades":6}},"equityTrades":[{"trade":0,"equity":50000,"date":"Start","pnl":0},{"trade":1,"equity":49730,"date":"2025-12-10","pnl":-270},{"trade":2,"equity":49625,"date":"2025-12-10","pnl":-105},{"trade":3,"equity":49590,"date":"2025-12-10","pnl":-35},{"trade":4,"equity":49490,"date":"2025-12-10","pnl":-100},{"trade":5,"equity":49340,"date":"2025-12-10","pnl":-150},{"trade":6,"equity":49210,"date":"2025-12-10","pnl":-130},{"trade":7,"equity":49215,"date":"2025-12-10","pnl":5},{"trade":8,"equity":49080,"date":"2025-12-10","pnl":-135},{"trade":9,"equity":48730,"date":"2025-12-10","pnl":-350},{"trade":10,"equity":49150,"date":"2025-12-10","pnl":420},{"trade":11,"equity":48850,"date":"2025-12-10","pnl":-300},{"trade":12,"equity":49020,"date":"2025-12-10","pnl":170},{"trade":13,"equity":48790,"date":"2025-12-10","pnl":-230},{"trade":14,"equity":48980,"date":"2025-12-10","pnl":190},{"trade":15,"equity":49375,"date":"2025-12-10","pnl":395},{"trade":16,"equity":49415,"date":"2025-12-10","pnl":40},{"trade":17,"equity":49485,"date":"2025-12-10","pnl":70},{"trade":18,"equity":49625,"date":"2025-12-10","pnl":140},{"trade":19,"equity":49587.5,"date":"2025-12-10","pnl":-37.5},{"trade":20,"equity":49537.5,"date":"2025-12-10","pnl":-50},{"trade":21,"equity":50157.5,"date":"2025-12-10","pnl":620},{"trade":22,"equity":50667.5,"date":"2025-12-11","pnl":510},{"trade":23,"equity":50477.5,"date":"2025-12-11","pnl":-190},{"trade":24,"equity":50457.5,"date":"2025-12-11","pnl":-20},{"trade":25,"equity":50617.5,"date":"2025-12-11","pnl":160},{"trade":26,"equity":50552.5,"date":"2025-12-12","pnl":-65},{"trade":27,"equity":50447.5,"date":"2025-12-12","pnl":-105},{"trade":28,"equity":50277.5,"date":"2025-12-12","pnl":-170},{"trade":29,"equity":50117.5,"date":"2025-12-12","pnl":-160},{"trade":30,"equity":50167.5,"date":"2025-12-12","pnl":50},{"trade":31,"equity":50237.5,"date":"2025-12-12","pnl":70},{"trade":32,"equity":50522.5,"date":"2025-12-12","pnl":285},{"trade":33,"equity":51112.5,"date":"2025-12-12","pnl":590},{"trade":34,"equity":51032.5,"date":"2025-12-15","pnl":-80},{"trade":35,"equity":50882.5,"date":"2025-12-15","pnl":-150},{"trade":36,"equity":51482.5,"date":"2025-12-15","pnl":600},{"trade":37,"equity":51762.5,"date":"2025-12-15","pnl":280},{"trade":38,"equity":51457.5,"date":"2025-12-16","pnl":-305},{"trade":39,"equity":51677.5,"date":"2025-12-16","pnl":220},{"trade":40,"equity":51767.5,"date":"2025-12-16","pnl":90},{"trade":41,"equity":51787.5,"date":"2025-12-16","pnl":20},{"trade":42,"equity":51782.5,"date":"2025-12-16","pnl":-5},{"trade":43,"equity":51712.5,"date":"2025-12-16","pnl":-70},{"trade":44,"equity":51702.5,"date":"2025-12-16","pnl":-10},{"trade":45,"equity":51472.5,"date":"2025-12-16","pnl":-230},{"trade":46,"equity":51967.5,"date":"2025-12-16","pnl":495},{"trade":47,"equity":51817.5,"date":"2025-12-17","pnl":-150},{"trade":48,"equity":51677.5,"date":"2025-12-17","pnl":-140},{"trade":49,"equity":51437.5,"date":"2025-12-17","pnl":-240},{"trade":50,"equity":51442.5,"date":"2025-12-17","pnl":5},{"trade":51,"equity":51512.5,"date":"2025-12-17","pnl":70},{"trade":52,"equity":51352.5,"date":"2025-12-17","pnl":-160},{"trade":53,"equity":51242.5,"date":"2025-12-17","pnl":-110},{"trade":54,"equity":51232.5,"date":"2025-12-17","pnl":-10},{"trade":55,"equity":51232.5,"date":"2025-12-17","pnl":0}],"equityDays":[{"day":0,"equity":50000,"date":"Start","pnl":0},{"day":1,"equity":50157.5,"date":"2025-12-10","pnl":157.5},{"day":2,"equity":50617.5,"date":"2025-12-11","pnl":460},{"day":3,"equity":51112.5,"date":"2025-12-12","pnl":495},{"day":4,"equity":51762.5,"date":"2025-12-15","pnl":650},{"day":5,"equity":51967.5,"date":"2025-12-16","pnl":205},{"day":6,"equity":51232.5,"date":"2025-12-17","pnl":-735}],"calendar":{"2025-11":{"10":{"pnl":157.5,"trades":21},"11":{"pnl":460,"trades":4},"12":{"pnl":495,"trades":8},"15":{"pnl":650,"trades":4},"16":{"pnl":205,"trades":9},"17":{"pnl":-735,"trades":9}}},"insights":[],"metadata":{"totalTrades":55,"netPL":1232.5,"netPLAfterFees":936.9999999999998,"totalFees":295.50000000000017,"winRate":41.81818181818181,"winningTrades":23,"losingTrades":31,"breakEvenTrades":1,"profitFactor":1.289149560117302,"avgWin":238.91304347826087,"avgLoss":137.5,"avgPL":17.03636363636363,"biggestWinner":620,"biggestLoser":-350,"maxDrawdown":1270,"maxDrawdownPercent":2.4438350892384664,"currentBalance":50937,"startingBalance":50000,"returnPercent":1.87,"generatedAt":"2025-12-17T11:53:10.296Z","version":"1.0"}}